session_keeper/__init__.py
session_keeper/__main__.py
session_keeper/cli.py
session_keeper/keeper/__init__.py
session_keeper/keeper/base.py
session_keeper/keeper/cli.py
session_keeper/session.py
session_keeper/storage/__init__.py
session_keeper/storage/abstract.py
session_keeper/storage/ejs.py
session_keeper/storage/exceptions.py
session_keeper/version.py
tg_session_keeper-0.1.2.dist-info/entry_points.txt
tg_session_keeper-0.1.2.dist-info/LICENSE
tg_session_keeper-0.1.2.dist-info/WHEEL
tg_session_keeper-0.1.2.dist-info/METADATA
tg_session_keeper-0.1.2.dist-info/RECORD
