Metadata-Version: 2.1
Name: tg-session-keeper
Version: 0.1.2
Summary: Консольная утилита для хранения Telegram-сессий.
Home-page: https://github.com/DavisDmitry/tg-session-keeper
License: MIT
Author: Dmitry Davis
Author-email: dmitrydavis@protonmail.com
Requires-Python: >=3.7,<4.0
Classifier: License :: OSI Approved :: MIT License
Classifier: Programming Language :: Python :: 3
Classifier: Programming Language :: Python :: 3.7
Classifier: Programming Language :: Python :: 3.8
Classifier: Programming Language :: Python :: 3.9
Classifier: Topic :: Utilities
Requires-Dist: Telethon (>=1.21.1,<2.0.0)
Requires-Dist: cryptography (>=3.4.7,<4.0.0)
Requires-Dist: tabulate (>=0.8.9,<0.9.0)
